dcim/__init__.py
dcim/builder.py
dcim/command_line.py
dcim/configuration.py
dcim/main.py
dcim/snmp.py
dcim/stream.py
dcim/time.py
dcim_fau-1.2.dist-info/LICENSE.txt
dcim_fau-1.2.dist-info/METADATA
dcim_fau-1.2.dist-info/WHEEL
dcim_fau-1.2.dist-info/entry_points.txt
dcim_fau-1.2.dist-info/top_level.txt
dcim_fau-1.2.dist-info/RECORD
