Metadata-Version: 2.1
Name: dcim-fau
Version: 1.2
Summary: UNKNOWN
Home-page: UNKNOWN
Author: Henry Herzfeld
Author-email: herzfeld2@gmail.com
License: MIT
Keywords: dcim,fau
Platform: UNKNOWN
Requires-Python: >=3.4
Requires-Dist: pyyaml
Requires-Dist: pysnmp
Requires-Dist: redis
Requires-Dist: walrus
Requires-Dist: pytest
